{
  "project_info": {
    "project_number": "433631481943",
    "project_id": "licienta-5b14f",
    "storage_bucket": "licienta-5b14f.appspot.com"
  },
  "client": [
    {
      "client_info": {
        "mobilesdk_app_id": "1:433631481943:android:db1167fdabe9e331799312",
        "android_client_info": {
          "package_name": "com.example.licienta"
        }
      },
      "oauth_client": [
        {
          "client_id": "433631481943-bdukei96oj9n2an0q1793l35j4um55ch.apps.googleusercontent.com",
          "client_type": 3
        }
      ],
      "api_key": [
        {
          "current_key": "AIzaSyAxp2fPXjB8u2PkUbuIP57Ob-DOmmnk7-g"
        }
      ],
      "services": {
        "appinvite_service": {
          "other_platform_oauth_client": [
            {
              "client_id": "433631481943-bdukei96oj9n2an0q1793l35j4um55ch.apps.googleusercontent.com",
              "client_type": 3
            }
          ]
        }
      }
    },
    {
      "client_info": {
        "mobilesdk_app_id": "1:433631481943:android:e4d1d430b5738f84799312",
        "android_client_info": {
          "package_name": "com.example.licienta2"
        }
      },
      "oauth_client": [
        {
          "client_id": "433631481943-bdukei96oj9n2an0q1793l35j4um55ch.apps.googleusercontent.com",
          "client_type": 3
        }
      ],
      "api_key": [
        {
          "current_key": "AIzaSyAxp2fPXjB8u2PkUbuIP57Ob-DOmmnk7-g"
        }
      ],
      "services": {
        "appinvite_service": {
          "other_platform_oauth_client": [
            {
              "client_id": "433631481943-bdukei96oj9n2an0q1793l35j4um55ch.apps.googleusercontent.com",
              "client_type": 3
            }
          ]
        }
      }
    }
  ],
  "configuration_version": "1"
}